madison_axi/__init__.py
madison_axi/axi.py
madison_axi/examples/__init__.py
madison_axi/examples/box.py
madison_axi/examples/circle.py
madison_axi/examples/flowers.py
madison_axi/examples/spiky_circle.py
madison_axi-0.1.1.dist-info/LICENSE.txt
madison_axi-0.1.1.dist-info/METADATA
madison_axi-0.1.1.dist-info/WHEEL
madison_axi-0.1.1.dist-info/top_level.txt
madison_axi-0.1.1.dist-info/RECORD
