Metadata-Version: 2.1
Name: madison-axi
Version: 0.1.1
Summary: A library that allows users to directly control an AxiDraw by writing Python code.
Home-page: http://github.com/jrheard/madison_axi
Author: JR Heard
Author-email: jrrrheard@gmail.com
License: MIT
Platform: UNKNOWN
Requires-Dist: requests
